{
  "showapi_res_body" : {
    "pagebean" : {
      "allNum" : 4064,
      "allPages" : 204,
      "contentlist" : [
        {
          "contentImg" : "http://app1.showapi.com/weixin_info/article/6e4349dd-0b03-42e5-b521-3dac2a376d19.jpg",
          "date" : "2015-09-24 16:18",
          "id" : "5603cbfa6e36eb7098f0bf4d",
          "title" : "不能让鸡蛋他妈守寡，太搞笑了!",
          "typeId" : "2",
          "typeName" : "段子手",
          "url" : "http://mp.weixin.qq.com/s?__biz=MjM5MTQxNjc3MA==&mid=211940068&idx=5&sn=2b788f42b354ab77210adc25fbe66bfa&3rd=MzA3MDU4NTYzMw==&scene=6#rd",
          "userLogo" : "http://app1.showapi.com/weixin_info/article/30edae6c-7f38-400e-ba57-8cb1ed358657.jpg",
          "userLogo_code" : "http://app1.showapi.com/weixin_info/article/ddc7d491-ded0-4502-a1ea-bd6075565212.jpg",
          "userName" : "男人女人那点事儿"
        },
        {
          "contentImg" : "http://app1.showapi.com/weixin_info/article/b8ab18a2-07f9-4f6f-889e-f64744cc3e68.jpg",
          "date" : "2015-09-24 16:07",
          "id" : "5603cbfa6e36eb7098f0bf42",
          "title" : "开心一刻，保证你笑到抽筋，要慢慢看!",
          "typeId" : "2",
          "typeName" : "段子手",
          "url" : "http://mp.weixin.qq.com/s?__biz=MzA4NTY4NTAxNg==&mid=212301907&idx=6&sn=64d839cb5cfa230805eed33d20e10f02&3rd=MzA3MDU4NTYzMw==&scene=6#rd",
          "userLogo" : "http://app1.showapi.com/weixin_info/article/78e38bb7-d841-4f66-bcbb-37638c27a7af.jpg",
          "userLogo_code" : "http://app1.showapi.com/weixin_info/article/24dcc2f4-4ecf-4f3b-aab6-4a2502a679ab.jpg",
          "userName" : "西纳维思"
        },
        {
          "contentImg" : "http://app1.showapi.com/weixin_info/article/613da78a-bb1a-4dd1-a4ac-5b75903b770e.jpg",
          "date" : "2015-09-24 15:56",
          "id" : "5603cbfa6e36eb7098f0bf1f",
          "title" : "[搞笑]5分钟，笑喷了2000000人!",
          "typeId" : "2",
          "typeName" : "段子手",
          "url" : "http://mp.weixin.qq.com/s?__biz=MzA5MTkzNzk4MA==&mid=211787170&idx=3&sn=ea6f8f6fbfb5511c06a60c2154b05f5e&3rd=MzA3MDU4NTYzMw==&scene=6#rd",
          "userLogo" : "http://app1.showapi.com/weixin_info/article/54f2aaa6-0787-488b-9e23-4d4ad059a5fb.jpg",
          "userLogo_code" : "http://app1.showapi.com/weixin_info/article/17aed2b9-0b77-490a-82b0-976fa212a29f.jpg",
          "userName" : "枣庄家电网"
        },
        {
          "contentImg" : "http://app1.showapi.com/weixin_info/article/66f48eff-efa9-4dc4-8a28-dbb8a2e31434.jpg",
          "date" : "2015-09-24 16:08",
          "id" : "5603cbfa6e36eb7098f0bf1e",
          "title" : "搞笑段子：你摸我的内裤干什么?",
          "typeId" : "2",
          "typeName" : "段子手",
          "url" : "http://mp.weixin.qq.com/s?__biz=MzI1NzAwNDk0MA==&mid=212270299&idx=4&sn=1cbd05b14c514fb063b994c98440b2a9&3rd=MzA3MDU4NTYzMw==&scene=6#rd",
          "userLogo" : "http://app1.showapi.com/weixin_info/article/ee977719-8a54-4c1a-86f2-df3ccd3e93d1.jpg",
          "userLogo_code" : "http://app1.showapi.com/weixin_info/article/ee4924c1-4e9d-4f53-965b-471ba4e93ab2.jpg",
          "userName" : "嫂子不要阿"
        },
        {
          "contentImg" : "http://app1.showapi.com/weixin_info/article/de5a2456-c5a1-4da8-977b-34f2f5a7a512.jpg",
          "date" : "2015-09-24 16:28",
          "id" : "5603cbfa6e36eb7098f0bf1d",
          "title" : "[搞笑]两个靓女在电话里相互“吹嘘”之后~",
          "typeId" : "2",
          "typeName" : "段子手",
          "url" : "http://mp.weixin.qq.com/s?__biz=MzA5OTY0NDMzNw==&mid=210540933&idx=5&sn=528387234fafdf3908fab37a5a3bd5f2&3rd=MzA3MDU4NTYzMw==&scene=6#rd",
          "userLogo" : "http://app1.showapi.com/weixin_info/article/f638e8e4-de61-44c8-9979-1b8c759886bd.jpg",
          "userLogo_code" : "http://app1.showapi.com/weixin_info/article/be9553af-14e6-4b04-aad6-dd6a8882d06a.jpg",
          "userName" : "横县大小事"
        },
        {
          "contentImg" : "http://app1.showapi.com/weixin_info/article/b11dbbd6-a239-4698-b31a-f6eceb3b0935.jpg",
          "date" : "2015-09-24 16:40",
          "id" : "5603cbfa6e36eb7098f0bf1c",
          "title" : "[每日一笑]已婚男人的奴婢生涯",
          "typeId" : "2",
          "typeName" : "段子手",
          "url" : "http://mp.weixin.qq.com/s?__biz=MjM5OTg0MTU0MQ==&mid=208425244&idx=8&sn=5b3aec9956633c4de34aed1ff8771edb&3rd=MzA3MDU4NTYzMw==&scene=6#rd",
          "userLogo" : "http://app1.showapi.com/weixin_info/article/23460cfa-1257-4550-bc7a-c18c2944f22d.jpg",
          "userLogo_code" : "http://app1.showapi.com/weixin_info/article/c2592973-8b04-4098-8b60-7abb84cb41fa.jpg",
          "userName" : "建水在线"
        },
        {
          "contentImg" : "http://app1.showapi.com/weixin_info/article/fdd57015-2ebe-4580-8b4e-f50cae35dac3.jpg",
          "date" : "2015-09-24 16:32",
          "id" : "5603cbf96e36eb7098f0bf1b",
          "title" : "[搞笑方言]唐伯虎点秋香..",
          "typeId" : "2",
          "typeName" : "段子手",
          "url" : "http://mp.weixin.qq.com/s?__biz=MjM5NDQwNjAwOQ==&mid=210085903&idx=3&sn=e94426211fdc541f1fb85818b32ce3b8&3rd=MzA3MDU4NTYzMw==&scene=6#rd",
          "userLogo" : "http://app1.showapi.com/weixin_info/article/8f377f6d-89c4-4a8c-a222-61843d1f50f0.jpg",
          "userLogo_code" : "http://app1.showapi.com/weixin_info/article/5b895559-a158-43c7-9c2e-4d0796bcec6c.jpg",
          "userName" : "掌上抚州"
        },
        {
          "contentImg" : "http://app1.showapi.com/weixin_info/article/87dd7e44-87c9-4fd8-b4bd-61332805f709.jpg",
          "date" : "2015-09-24 16:34",
          "id" : "5603cbf96e36eb7098f0bee9",
          "title" : "搞笑就这嗨仔的智商，还想打劫美女..",
          "typeId" : "2",
          "typeName" : "段子手",
          "url" : "http://mp.weixin.qq.com/s?__biz=MzA5NDQ3MjQxMg==&mid=211054846&idx=7&sn=a23b5df72546832159ff187cbbbf78e5&3rd=MzA3MDU4NTYzMw==&scene=6#rd",
          "userLogo" : "http://app1.showapi.com/weixin_info/article/2c33bb21-223f-4f8f-9ffe-3992ba3f1253.jpg",
          "userLogo_code" : "http://app1.showapi.com/weixin_info/article/a1da2e19-c358-42a5-874d-10e302ece872.jpg",
          "userName" : "防城港微生活"
        },
        {
          "contentImg" : "http://app1.showapi.com/weixin_info/article/e4d1f0f7-eb0e-49aa-aac9-c5d47f6fb639.jpg",
          "date" : "2015-09-24 14:50",
          "id" : "5603bded6e36eb7098f0a886",
          "title" : "搞笑视频 土豪三亚吃霸王餐被逼跳楼",
          "typeId" : "2",
          "typeName" : "段子手",
          "url" : "http://mp.weixin.qq.com/s?__biz=MzA5MTAyMTM5Mg==&mid=208853814&idx=1&sn=235fddd73c6581c49c7028fcc8e265de&3rd=MzA3MDU4NTYzMw==&scene=6#rd",
          "userLogo" : "http://app1.showapi.com/weixin_info/article/df90f3d0-4dfd-4d84-85db-23e30133623f.jpg",
          "userLogo_code" : "http://app1.showapi.com/weixin_info/article/fed0030c-8ddf-44e3-997a-f20d9e319ab0.jpg",
          "userName" : "搞笑电影"
        },
        {
          "contentImg" : "http://app1.showapi.com/weixin_info/article/0b748c7f-3b25-4c74-be8e-b36c0be50b81.jpg",
          "date" : "2015-09-24 15:04",
          "id" : "5603bded6e36eb7098f0a884",
          "title" : "[爆笑]内蒙版潘金莲和西门庆偷情",
          "typeId" : "2",
          "typeName" : "段子手",
          "url" : "http://mp.weixin.qq.com/s?__biz=MzA4NzEyMTQ3Mw==&mid=210053144&idx=7&sn=6c8606a0652fef0c572e94b4d27a9b03&3rd=MzA3MDU4NTYzMw==&scene=6#rd",
          "userLogo" : "http://app1.showapi.com/weixin_info/article/07277530-31f6-4188-8ac6-52131bc43d26.jpg",
          "userLogo_code" : "http://app1.showapi.com/weixin_info/article/8ce6c991-3100-4838-81b4-6439a1caf4d6.jpg",
          "userName" : "茶余饭后"
        },
        {
          "contentImg" : "http://app1.showapi.com/weixin_info/article/24e8d516-064c-4b39-b55c-17a2671a34dd.jpg",
          "date" : "2015-09-24 15:09",
          "id" : "5603bded6e36eb7098f0a882",
          "title" : "当表情图配上搞笑段子，笑喷了!",
          "typeId" : "2",
          "typeName" : "段子手",
          "url" : "http://mp.weixin.qq.com/s?__biz=MzAxNTAxMzc1OQ==&mid=212220779&idx=1&sn=cd318dd5eac1734225b11146ae5ea8b1&3rd=MzA3MDU4NTYzMw==&scene=6#rd",
          "userLogo" : "http://app1.showapi.com/weixin_info/article/c12d2ae9-8347-436f-b649-336e1bd293b1.jpg",
          "userLogo_code" : "http://app1.showapi.com/weixin_info/article/6b5cfd2a-c7a6-4a0c-a26c-545a2a567aa1.jpg",
          "userName" : "爆笑搞笑图片"
        },
        {
          "contentImg" : "http://app1.showapi.com/weixin_info/article/035d7772-8d85-4cbb-8289-f030470e8d5e.jpg",
          "date" : "2015-09-24 15:08",
          "id" : "5603bded6e36eb7098f0a881",
          "title" : "[幽默笑话]媳妇已经绑起来了",
          "typeId" : "2",
          "typeName" : "段子手",
          "url" : "http://mp.weixin.qq.com/s?__biz=MzIwNjAxNTAxNA==&mid=272748311&idx=3&sn=4c21ce6ce50016367589406c059193bb&3rd=MzA3MDU4NTYzMw==&scene=6#rd",
          "userLogo" : "http://app1.showapi.com/weixin_info/article/71e88d32-ba78-4d3e-89b2-d0775cda22a9.jpg",
          "userLogo_code" : "http://app1.showapi.com/weixin_info/article/378379ae-b007-4985-a183-2b468c7c7191.jpg",
          "userName" : "我爱晒生活"
        },
        {
          "contentImg" : "http://app1.showapi.com/weixin_info/article/9de55197-8393-4651-b72c-ac4bf0865c99.jpg",
          "date" : "2015-09-24 15:09",
          "id" : "5603bded6e36eb7098f0a880",
          "title" : "邮段子 自古泳池产人才，你们是认真来搞笑的吧!",
          "typeId" : "2",
          "typeName" : "段子手",
          "url" : "http://mp.weixin.qq.com/s?__biz=MjM5NjU3MzU2Mw==&mid=212143796&idx=5&sn=77ab9966f80313ed15d09bf7c9498555&3rd=MzA3MDU4NTYzMw==&scene=6#rd",
          "userLogo" : "http://app1.showapi.com/weixin_info/article/fca0bce5-40de-4a6a-bd16-699a9653d4a4.jpg",
          "userLogo_code" : "http://app1.showapi.com/weixin_info/article/2ec70fe3-77b6-4541-9a13-9ceff17ab9c1.jpg",
          "userName" : "邮乐"
        },
        {
          "contentImg" : "http://app1.showapi.com/weixin_info/article/6f96ab45-e04b-4869-bbae-fb8c29e605b5.jpg",
          "date" : "2015-09-24 15:20",
          "id" : "5603bded6e36eb7098f0a87f",
          "title" : "搞笑：杀姐姐的对白哈哈哈，笑死我了!!",
          "typeId" : "2",
          "typeName" : "段子手",
          "url" : "http://mp.weixin.qq.com/s?__biz=MzA3NzM4OTQzMg==&mid=211541947&idx=6&sn=2c69648f04dbb53425a6e65915d58a0c&3rd=MzA3MDU4NTYzMw==&scene=6#rd",
          "userLogo" : "http://app1.showapi.com/weixin_info/article/e778054d-df3b-414f-a759-b9cabe48512f.jpg",
          "userLogo_code" : "http://app1.showapi.com/weixin_info/article/1e81147a-1660-4dfc-8f45-5f62044e78be.jpg",
          "userName" : "叽歪搞笑集中营"
        },
        {
          "contentImg" : "http://app1.showapi.com/weixin_info/article/7b92246e-ac8f-429c-a2df-886aa6557175.jpg",
          "date" : "2015-09-24 15:39",
          "id" : "5603bded6e36eb7098f0a87e",
          "title" : "[搞笑图片]绝对笑翻你!",
          "typeId" : "2",
          "typeName" : "段子手",
          "url" : "http://mp.weixin.qq.com/s?__biz=MjM5NjExOTI3OQ==&mid=209687334&idx=4&sn=ea811da3df3087e0a16c2e8636faac1c&3rd=MzA3MDU4NTYzMw==&scene=6#rd",
          "userLogo" : "http://app1.showapi.com/weixin_info/article/43d01a76-4512-4255-be52-b764cc482551.jpg",
          "userLogo_code" : "http://app1.showapi.com/weixin_info/article/69b55dff-617b-4f22-ac3d-f854a3e91dba.jpg",
          "userName" : "高速公路路况信息平台"
        },
        {
          "contentImg" : "http://app1.showapi.com/weixin_info/article/f5457005-da0e-4dc2-b4cd-7f4d40feff68.jpg",
          "date" : "2015-09-24 15:46",
          "id" : "5603bdec6e36eb7098f0a87d",
          "title" : "这个宝宝才三个月!就这么搞笑!太逗了",
          "typeId" : "2",
          "typeName" : "段子手",
          "url" : "http://mp.weixin.qq.com/s?__biz=MzA4ODQ5MjQwNQ==&mid=208769841&idx=5&sn=7ed273b8df5e2815d4ab921f1d75fb21&3rd=MzA3MDU4NTYzMw==&scene=6#rd",
          "userLogo" : "http://app1.showapi.com/weixin_info/article/d461c703-959b-4e22-87a8-8cde57cf79b4.jpg",
          "userLogo_code" : "http://app1.showapi.com/weixin_info/article/c5c1ed83-ac35-4b10-a14b-04812d343093.jpg",
          "userName" : "乳山通"
        },
        {
          "contentImg" : "http://app1.showapi.com/weixin_info/article/d3898d49-fae8-4ced-9698-6074b65464e6.jpg",
          "date" : "2015-09-24 15:45",
          "id" : "5603bdec6e36eb7098f0a87a",
          "title" : "一群禽兽!!是搞笑还是现实..",
          "typeId" : "2",
          "typeName" : "段子手",
          "url" : "http://mp.weixin.qq.com/s?__biz=MjM5MTIxNzIzNg==&mid=211128968&idx=1&sn=5078e448dec53e4b654f745d9fb7ba19&3rd=MzA3MDU4NTYzMw==&scene=6#rd",
          "userLogo" : "http://app1.showapi.com/weixin_info/article/87e5a46f-a2b0-4338-a60b-c9a5dcd7c9df.jpg",
          "userLogo_code" : "http://app1.showapi.com/weixin_info/article/7da009ad-a060-4d7d-87e8-0a6900f4f177.jpg",
          "userName" : "youmox幽默X咪咪6566搞笑139搞笑255"
        },
        {
          "contentImg" : "http://app1.showapi.com/weixin_info/article/996aa26e-4fd2-4a0e-a34f-30530e7d0aa7.jpg",
          "date" : "2015-09-24 13:52",
          "id" : "5603afde6e36eb7098f089d9",
          "title" : "爆笑一刻 惊呆了!6岁萌妹子就该这样教育吵架的...",
          "typeId" : "2",
          "typeName" : "段子手",
          "url" : "http://mp.weixin.qq.com/s?__biz=MjM5MDAzNjM2MA==&mid=209961851&idx=7&sn=2ebcce101f629a8d34c14a4caebd5140&3rd=MzA3MDU4NTYzMw==&scene=6#rd",
          "userLogo" : "http://app1.showapi.com/weixin_info/article/a190a4c1-6c9e-4ddc-af28-0e65695daa92.jpg",
          "userLogo_code" : "http://app1.showapi.com/weixin_info/article/04c0c7e0-2d41-45f3-a72b-95830448105e.jpg",
          "userName" : "山东卫视"
        },
        {
          "contentImg" : "http://app1.showapi.com/weixin_info/article/f4bca069-c384-480e-af36-312583224f40.jpg",
          "date" : "2015-09-24 14:36",
          "id" : "5603afde6e36eb7098f089a5",
          "title" : "毁童年!瞎狗眼!原来还珠格格是部搞笑片..",
          "typeId" : "2",
          "typeName" : "段子手",
          "url" : "http://mp.weixin.qq.com/s?__biz=MjM5ODk3MTI3MQ==&mid=212902986&idx=4&sn=ea5dbfb309323a0a4c8f0b1bfa54253e&3rd=MzA3MDU4NTYzMw==&scene=6#rd",
          "userLogo" : "http://app1.showapi.com/weixin_info/article/50aa9cf2-3196-472d-b9b9-5f7547bab1c0.jpg",
          "userLogo_code" : "http://app1.showapi.com/weixin_info/article/0e80e6b0-1381-4775-8611-e8b1287d2f19.jpg",
          "userName" : "京东金融社区"
        },
        {
          "contentImg" : "http://app1.showapi.com/weixin_info/article/1e07b1e2-2222-4f7a-b111-6e6696592766.jpg",
          "date" : "2015-09-24 13:58",
          "id" : "5603afde6e36eb7098f089a4",
          "title" : "妈呀!太搞笑啦!给亲们乐一乐!",
          "typeId" : "2",
          "typeName" : "段子手",
          "url" : "http://mp.weixin.qq.com/s?__biz=MzA5NTE5MzE5MA==&mid=213690573&idx=7&sn=d0732094ce462dfdf8e15be46e1c8fa1&3rd=MzA3MDU4NTYzMw==&scene=6#rd",
          "userLogo" : "http://app1.showapi.com/weixin_info/article/8e6f6b28-b7cd-4127-854e-796a1f011112.jpg",
          "userLogo_code" : "http://app1.showapi.com/weixin_info/article/23ea18fd-fdfd-44ef-8aa5-0e39d0a94999.jpg",
          "userName" : "婷婷有话说"
        }
      ],
      "currentPage" : 1,
      "maxResult" : 20
    },
    "ret_code" : 0
  },
  "showapi_res_code" : 0,
  "showapi_res_error" : ""
}